{"growth": "linear", "n_changepoints": 13, "specified_changepoints": false, "changepoint_range": 0.8, "yearly_seasonality": "auto", "weekly_seasonality": "auto", "daily_seasonality": "auto", "seasonality_mode": "additive", "seasonality_prior_scale": 10.0, "changepoint_prior_scale": 0.05, "holidays_prior_scale": 10.0, "mcmc_samples": 0, "interval_width": 0.8, "uncertainty_samples": 1000, "y_scale": 215000.0, "logistic_floor": false, "country_holidays": null, "component_modes": {"additive": ["yearly", "additive_terms", "extra_regressors_additive", "holidays"], "multiplicative": ["multiplicative_terms", "extra_regressors_multiplicative"]}, "changepoints": "{\"name\":\"ds\",\"index\":[1,2,3,4,5,6,7,8,9,10,11,12,13],\"data\":[\"2017-10-27T00:00:00.000\",\"2018-04-25T00:00:00.000\",\"2018-06-18T00:00:00.000\",\"2018-10-16T00:00:00.000\",\"2019-02-05T00:00:00.000\",\"2020-01-31T00:00:00.000\",\"2020-06-18T00:00:00.000\",\"2020-08-27T00:00:00.000\",\"2020-10-07T00:00:00.000\",\"2021-01-20T00:00:00.000\",\"2021-01-28T00:00:00.000\",\"2021-09-20T00:00:00.000\",\"2021-10-18T00:00:00.000\"]}", "history_dates": "{\"name\":\"ds\",\"index\":[0,1,2,3,4,5,6,7,8,9,10,11,12,13,14,15,16,17],\"data\":[\"2017-06-22T00:00:00.000\",\"2017-10-27T00:00:00.000\",\"2018-04-25T00:00:00.000\",\"2018-06-18T00:00:00.000\",\"2018-10-16T00:00:00.000\",\"2019-02-05T00:00:00.000\",\"2020-01-31T00:00:00.000\",\"2020-06-18T00:00:00.000\",\"2020-08-27T00:00:00.000\",\"2020-10-07T00:00:00.000\",\"2021-01-20T00:00:00.000\",\"2021-01-28T00:00:00.000\",\"2021-09-20T00:00:00.000\",\"2021-10-18T00:00:00.000\",\"2022-02-10T00:00:00.000\",\"2022-03-28T00:00:00.000\",\"2022-09-02T00:00:00.000\",\"2022-10-19T00:00:00.000\"]}", "train_holiday_names": null, "start": 1498089600.0, "t_scale": 168048000.0, "holidays": null, "history": "{\"schema\":{\"fields\":[{\"name\":\"y\",\"type\":\"number\"},{\"name\":\"ds\",\"type\":\"datetime\"},{\"name\":\"floor\",\"type\":\"integer\"},{\"name\":\"t\",\"type\":\"number\"},{\"name\":\"y_scaled\",\"type\":\"number\"}],\"pandas_version\":\"1.4.0\"},\"data\":[{\"y\":140000.0,\"ds\":\"2017-06-22T00:00:00.000\",\"floor\":0,\"t\":0.0,\"y_scaled\":0.6511627907},{\"y\":119000.0,\"ds\":\"2017-10-27T00:00:00.000\",\"floor\":0,\"t\":0.0652956298,\"y_scaled\":0.5534883721},{\"y\":118000.0,\"ds\":\"2018-04-25T00:00:00.000\",\"floor\":0,\"t\":0.157840617,\"y_scaled\":0.5488372093},{\"y\":141000.0,\"ds\":\"2018-06-18T00:00:00.000\",\"floor\":0,\"t\":0.1856041131,\"y_scaled\":0.6558139535},{\"y\":124999.0,\"ds\":\"2018-10-16T00:00:00.000\",\"floor\":0,\"t\":0.2473007712,\"y_scaled\":0.5813906977},{\"y\":138000.0,\"ds\":\"2019-02-05T00:00:00.000\",\"floor\":0,\"t\":0.3048843188,\"y_scaled\":0.6418604651},{\"y\":105000.0,\"ds\":\"2020-01-31T00:00:00.000\",\"floor\":0,\"t\":0.4899742931,\"y_scaled\":0.488372093},{\"y\":140000.0,\"ds\":\"2020-06-18T00:00:00.000\",\"floor\":0,\"t\":0.5614395887,\"y_scaled\":0.6511627907},{\"y\":125000.0,\"ds\":\"2020-08-27T00:00:00.000\",\"floor\":0,\"t\":0.5974293059,\"y_scaled\":0.5813953488},{\"y\":120000.0,\"ds\":\"2020-10-07T00:00:00.000\",\"floor\":0,\"t\":0.6185089974,\"y_scaled\":0.5581395349},{\"y\":130000.0,\"ds\":\"2021-01-20T00:00:00.000\",\"floor\":0,\"t\":0.6724935733,\"y_scaled\":0.6046511628},{\"y\":130000.0,\"ds\":\"2021-01-28T00:00:00.000\",\"floor\":0,\"t\":0.6766066838,\"y_scaled\":0.6046511628},{\"y\":120000.0,\"ds\":\"2021-09-20T00:00:00.000\",\"floor\":0,\"t\":0.7974293059,\"y_scaled\":0.5581395349},{\"y\":100000.0,\"ds\":\"2021-10-18T00:00:00.000\",\"floor\":0,\"t\":0.8118251928,\"y_scaled\":0.4651162791},{\"y\":109000.0,\"ds\":\"2022-02-10T00:00:00.000\",\"floor\":0,\"t\":0.8709511568,\"y_scaled\":0.5069767442},{\"y\":160000.0,\"ds\":\"2022-03-28T00:00:00.000\",\"floor\":0,\"t\":0.8946015424,\"y_scaled\":0.7441860465},{\"y\":215000.0,\"ds\":\"2022-09-02T00:00:00.000\",\"floor\":0,\"t\":0.9758354756,\"y_scaled\":1.0},{\"y\":109000.0,\"ds\":\"2022-10-19T00:00:00.000\",\"floor\":0,\"t\":1.0,\"y_scaled\":0.5069767442}]}", "train_component_cols": "{\"schema\":{\"fields\":[{\"name\":\"additive_terms\",\"type\":\"integer\"},{\"name\":\"yearly\",\"type\":\"integer\"},{\"name\":\"multiplicative_terms\",\"type\":\"integer\"}],\"pandas_version\":\"1.4.0\"},\"data\":[{\"additive_terms\":1,\"yearly\":1,\"multiplicative_terms\":0},{\"additive_terms\":1,\"yearly\":1,\"multiplicative_terms\":0},{\"additive_terms\":1,\"yearly\":1,\"multiplicative_terms\":0},{\"additive_terms\":1,\"yearly\":1,\"multiplicative_terms\":0},{\"additive_terms\":1,\"yearly\":1,\"multiplicative_terms\":0},{\"additive_terms\":1,\"yearly\":1,\"multiplicative_terms\":0},{\"additive_terms\":1,\"yearly\":1,\"multiplicative_terms\":0},{\"additive_terms\":1,\"yearly\":1,\"multiplicative_terms\":0},{\"additive_terms\":1,\"yearly\":1,\"multiplicative_terms\":0},{\"additive_terms\":1,\"yearly\":1,\"multiplicative_terms\":0},{\"additive_terms\":1,\"yearly\":1,\"multiplicative_terms\":0},{\"additive_terms\":1,\"yearly\":1,\"multiplicative_terms\":0},{\"additive_terms\":1,\"yearly\":1,\"multiplicative_terms\":0},{\"additive_terms\":1,\"yearly\":1,\"multiplicative_terms\":0},{\"additive_terms\":1,\"yearly\":1,\"multiplicative_terms\":0},{\"additive_terms\":1,\"yearly\":1,\"multiplicative_terms\":0},{\"additive_terms\":1,\"yearly\":1,\"multiplicative_terms\":0},{\"additive_terms\":1,\"yearly\":1,\"multiplicative_terms\":0},{\"additive_terms\":1,\"yearly\":1,\"multiplicative_terms\":0},{\"additive_terms\":1,\"yearly\":1,\"multiplicative_terms\":0}]}", "changepoints_t": [0.06529562982005141, 0.15784061696658097, 0.18560411311053984, 0.24730077120822622, 0.30488431876606686, 0.489974293059126, 0.5614395886889461, 0.5974293059125964, 0.6185089974293059, 0.6724935732647815, 0.6766066838046273, 0.7974293059125964, 0.8118251928020566], "seasonalities": [["yearly"], {"yearly": {"period": 365.25, "fourier_order": 10, "prior_scale": 10.0, "mode": "additive", "condition_name": null}}], "extra_regressors": [[], {}], "fit_kwargs": {}, "params": {"lp__": [[376.465]], "k": [[-0.455107]], "m": [[-0.756796]], "delta": [[-8.71988e-11, 7.52618e-11, -1.67506e-09, -1.55654e-09, 1.41104e-10, -0.000742655, -2.46883e-10, -4.90014e-11, 9.68159e-10, 0.0690468, 0.310169, 0.0495848, 0.0677957]], "sigma_obs": [[4.29644e-10]], "beta": [[-5.48588, -5.20484, -3.28767, 3.06043, -2.84268, 6.97261, 8.10564, -1.70972, -2.79251, -4.33784, -1.74649, -5.70922, -3.49693, -2.12055, -3.31414, 0.808694, 6.51858, 1.37608, 0.362737, -4.66108]], "trend": [[-0.756796, -0.786513, -0.828631, -0.841266, -0.869344, -0.895551, -0.979787, -1.01236, -1.02877, -1.03838, -1.06299, -1.06458, -1.07384, -1.07423, -1.07182, -1.07085, -1.06754, -1.06656]]}, "__prophet_version": "1.1.2"}