{"growth": "linear", "n_changepoints": 5, "specified_changepoints": false, "changepoint_range": 0.8, "yearly_seasonality": "auto", "weekly_seasonality": "auto", "daily_seasonality": "auto", "seasonality_mode": "additive", "seasonality_prior_scale": 10.0, "changepoint_prior_scale": 0.05, "holidays_prior_scale": 10.0, "mcmc_samples": 0, "interval_width": 0.8, "uncertainty_samples": 1000, "y_scale": 1685000.0, "logistic_floor": false, "country_holidays": null, "component_modes": {"additive": ["yearly", "additive_terms", "extra_regressors_additive", "holidays"], "multiplicative": ["multiplicative_terms", "extra_regressors_multiplicative"]}, "changepoints": "{\"name\":\"ds\",\"index\":[1,2,3,4,5],\"data\":[\"2018-03-13T00:00:00.000\",\"2019-06-05T00:00:00.000\",\"2019-06-19T00:00:00.000\",\"2019-07-02T00:00:00.000\",\"2019-08-19T00:00:00.000\"]}", "history_dates": "{\"name\":\"ds\",\"index\":[0,1,2,3,4,5,6,7],\"data\":[\"2017-02-24T00:00:00.000\",\"2018-03-13T00:00:00.000\",\"2019-06-05T00:00:00.000\",\"2019-06-19T00:00:00.000\",\"2019-07-02T00:00:00.000\",\"2019-08-19T00:00:00.000\",\"2020-05-12T00:00:00.000\",\"2020-05-20T00:00:00.000\"]}", "train_holiday_names": null, "start": 1487894400.0, "t_scale": 102038400.0, "holidays": null, "history": "{\"schema\":{\"fields\":[{\"name\":\"y\",\"type\":\"number\"},{\"name\":\"ds\",\"type\":\"datetime\"},{\"name\":\"floor\",\"type\":\"integer\"},{\"name\":\"t\",\"type\":\"number\"},{\"name\":\"y_scaled\",\"type\":\"number\"}],\"pandas_version\":\"1.4.0\"},\"data\":[{\"y\":1525000.0,\"ds\":\"2017-02-24T00:00:00.000\",\"floor\":0,\"t\":0.0,\"y_scaled\":0.9050445104},{\"y\":1438500.0,\"ds\":\"2018-03-13T00:00:00.000\",\"floor\":0,\"t\":0.3234546994,\"y_scaled\":0.8537091988},{\"y\":1600000.0,\"ds\":\"2019-06-05T00:00:00.000\",\"floor\":0,\"t\":0.7036409822,\"y_scaled\":0.9495548961},{\"y\":1575000.0,\"ds\":\"2019-06-19T00:00:00.000\",\"floor\":0,\"t\":0.7154953429,\"y_scaled\":0.9347181009},{\"y\":1312500.0,\"ds\":\"2019-07-02T00:00:00.000\",\"floor\":0,\"t\":0.7265029636,\"y_scaled\":0.7789317507},{\"y\":1685000.0,\"ds\":\"2019-08-19T00:00:00.000\",\"floor\":0,\"t\":0.767146486,\"y_scaled\":1.0},{\"y\":750000.0,\"ds\":\"2020-05-12T00:00:00.000\",\"floor\":0,\"t\":0.9932260796,\"y_scaled\":0.4451038576},{\"y\":1475000.0,\"ds\":\"2020-05-20T00:00:00.000\",\"floor\":0,\"t\":1.0,\"y_scaled\":0.8753709199}]}", "train_component_cols": "{\"schema\":{\"fields\":[{\"name\":\"additive_terms\",\"type\":\"integer\"},{\"name\":\"yearly\",\"type\":\"integer\"},{\"name\":\"multiplicative_terms\",\"type\":\"integer\"}],\"pandas_version\":\"1.4.0\"},\"data\":[{\"additive_terms\":1,\"yearly\":1,\"multiplicative_terms\":0},{\"additive_terms\":1,\"yearly\":1,\"multiplicative_terms\":0},{\"additive_terms\":1,\"yearly\":1,\"multiplicative_terms\":0},{\"additive_terms\":1,\"yearly\":1,\"multiplicative_terms\":0},{\"additive_terms\":1,\"yearly\":1,\"multiplicative_terms\":0},{\"additive_terms\":1,\"yearly\":1,\"multiplicative_terms\":0},{\"additive_terms\":1,\"yearly\":1,\"multiplicative_terms\":0},{\"additive_terms\":1,\"yearly\":1,\"multiplicative_terms\":0},{\"additive_terms\":1,\"yearly\":1,\"multiplicative_terms\":0},{\"additive_terms\":1,\"yearly\":1,\"multiplicative_terms\":0},{\"additive_terms\":1,\"yearly\":1,\"multiplicative_terms\":0},{\"additive_terms\":1,\"yearly\":1,\"multiplicative_terms\":0},{\"additive_terms\":1,\"yearly\":1,\"multiplicative_terms\":0},{\"additive_terms\":1,\"yearly\":1,\"multiplicative_terms\":0},{\"additive_terms\":1,\"yearly\":1,\"multiplicative_terms\":0},{\"additive_terms\":1,\"yearly\":1,\"multiplicative_terms\":0},{\"additive_terms\":1,\"yearly\":1,\"multiplicative_terms\":0},{\"additive_terms\":1,\"yearly\":1,\"multiplicative_terms\":0},{\"additive_terms\":1,\"yearly\":1,\"multiplicative_terms\":0},{\"additive_terms\":1,\"yearly\":1,\"multiplicative_terms\":0}]}", "changepoints_t": [0.32345469940728194, 0.7036409822184589, 0.7154953429297206, 0.7265029635901779, 0.7671464860287892], "seasonalities": [["yearly"], {"yearly": {"period": 365.25, "fourier_order": 10, "prior_scale": 10.0, "mode": "additive", "condition_name": null}}], "extra_regressors": [[], {}], "fit_kwargs": {}, "params": {"lp__": [[173.601]], "k": [[0.414093]], "m": [[-0.106676]], "delta": [[-4.65167e-09, -2.6313e-09, 1.92663e-09, 1.29884e-09, -3.70585e-09]], "sigma_obs": [[3.69857e-10]], "beta": [[-0.579819, 1.94231, -1.97931, 0.218912, 1.12135, -1.29994, 0.681371, -1.62113, 1.64485, 0.386427, 0.0750026, 1.52895, 0.772167, -0.0334069, -0.89821, -0.614834, -0.73343, -2.38074, 0.49822, -0.489796]], "trend": [[-0.106676, 0.027264, 0.184697, 0.189605, 0.194164, 0.210994, 0.304612, 0.307417]]}, "__prophet_version": "1.1.2"}