{"growth": "linear", "n_changepoints": 3, "specified_changepoints": false, "changepoint_range": 0.8, "yearly_seasonality": "auto", "weekly_seasonality": "auto", "daily_seasonality": "auto", "seasonality_mode": "additive", "seasonality_prior_scale": 10.0, "changepoint_prior_scale": 0.05, "holidays_prior_scale": 10.0, "mcmc_samples": 0, "interval_width": 0.8, "uncertainty_samples": 1000, "y_scale": 576086.9565, "logistic_floor": false, "country_holidays": null, "component_modes": {"additive": ["yearly", "additive_terms", "extra_regressors_additive", "holidays"], "multiplicative": ["multiplicative_terms", "extra_regressors_multiplicative"]}, "changepoints": "{\"name\":\"ds\",\"index\":[1,2,3],\"data\":[\"2017-10-03T00:00:00.000\",\"2018-02-27T00:00:00.000\",\"2019-03-26T00:00:00.000\"]}", "history_dates": "{\"name\":\"ds\",\"index\":[0,1,2,3,4],\"data\":[\"2017-06-13T00:00:00.000\",\"2017-10-03T00:00:00.000\",\"2018-02-27T00:00:00.000\",\"2019-03-26T00:00:00.000\",\"2021-06-28T00:00:00.000\"]}", "train_holiday_names": null, "start": 1497312000.0, "t_scale": 127526400.0, "holidays": null, "history": "{\"schema\":{\"fields\":[{\"name\":\"y\",\"type\":\"number\"},{\"name\":\"ds\",\"type\":\"datetime\"},{\"name\":\"floor\",\"type\":\"integer\"},{\"name\":\"t\",\"type\":\"number\"},{\"name\":\"y_scaled\",\"type\":\"number\"}],\"pandas_version\":\"1.4.0\"},\"data\":[{\"y\":245131.5778,\"ds\":\"2017-06-13T00:00:00.000\",\"floor\":0,\"t\":0.0,\"y_scaled\":0.4255114181},{\"y\":576086.9565,\"ds\":\"2017-10-03T00:00:00.000\",\"floor\":0,\"t\":0.0758807588,\"y_scaled\":1.0},{\"y\":369230.7692,\"ds\":\"2018-02-27T00:00:00.000\",\"floor\":0,\"t\":0.1754742547,\"y_scaled\":0.6409288824},{\"y\":423076.9231,\"ds\":\"2019-03-26T00:00:00.000\",\"floor\":0,\"t\":0.4410569106,\"y_scaled\":0.7343976779},{\"y\":228000.0,\"ds\":\"2021-06-28T00:00:00.000\",\"floor\":0,\"t\":1.0,\"y_scaled\":0.3957735849}]}", "train_component_cols": "{\"schema\":{\"fields\":[{\"name\":\"additive_terms\",\"type\":\"integer\"},{\"name\":\"yearly\",\"type\":\"integer\"},{\"name\":\"multiplicative_terms\",\"type\":\"integer\"}],\"pandas_version\":\"1.4.0\"},\"data\":[{\"additive_terms\":1,\"yearly\":1,\"multiplicative_terms\":0},{\"additive_terms\":1,\"yearly\":1,\"multiplicative_terms\":0},{\"additive_terms\":1,\"yearly\":1,\"multiplicative_terms\":0},{\"additive_terms\":1,\"yearly\":1,\"multiplicative_terms\":0},{\"additive_terms\":1,\"yearly\":1,\"multiplicative_terms\":0},{\"additive_terms\":1,\"yearly\":1,\"multiplicative_terms\":0},{\"additive_terms\":1,\"yearly\":1,\"multiplicative_terms\":0},{\"additive_terms\":1,\"yearly\":1,\"multiplicative_terms\":0},{\"additive_terms\":1,\"yearly\":1,\"multiplicative_terms\":0},{\"additive_terms\":1,\"yearly\":1,\"multiplicative_terms\":0},{\"additive_terms\":1,\"yearly\":1,\"multiplicative_terms\":0},{\"additive_terms\":1,\"yearly\":1,\"multiplicative_terms\":0},{\"additive_terms\":1,\"yearly\":1,\"multiplicative_terms\":0},{\"additive_terms\":1,\"yearly\":1,\"multiplicative_terms\":0},{\"additive_terms\":1,\"yearly\":1,\"multiplicative_terms\":0},{\"additive_terms\":1,\"yearly\":1,\"multiplicative_terms\":0},{\"additive_terms\":1,\"yearly\":1,\"multiplicative_terms\":0},{\"additive_terms\":1,\"yearly\":1,\"multiplicative_terms\":0},{\"additive_terms\":1,\"yearly\":1,\"multiplicative_terms\":0},{\"additive_terms\":1,\"yearly\":1,\"multiplicative_terms\":0}]}", "changepoints_t": [0.07588075880758807, 0.17547425474254744, 0.4410569105691057], "seasonalities": [["yearly"], {"yearly": {"period": 365.25, "fourier_order": 10, "prior_scale": 10.0, "mode": "additive", "condition_name": null}}], "extra_regressors": [[], {}], "fit_kwargs": {}, "params": {"lp__": [[108.992]], "k": [[4.70384]], "m": [[3.20313]], "delta": [[-2.57417e-11, 2.26759e-10, 7.40655e-10]], "sigma_obs": [[2.35414e-10]], "beta": [[-1.5916, 3.59372, 2.46173, 2.37733, 7.65867, 2.55091, -3.76055, -5.85533, -3.64596, -1.91482, -0.0953142, -4.57343, -3.56715, -3.87315, -1.47521, -0.973118, 3.20131, 1.41593, 2.82283, 3.46658]], "trend": [[3.20313, 3.56006, 4.02853, 5.27779, 7.90697]]}, "__prophet_version": "1.1.2"}