{"growth": "linear", "n_changepoints": 3, "specified_changepoints": false, "changepoint_range": 0.8, "yearly_seasonality": "auto", "weekly_seasonality": "auto", "daily_seasonality": "auto", "seasonality_mode": "additive", "seasonality_prior_scale": 10.0, "changepoint_prior_scale": 0.05, "holidays_prior_scale": 10.0, "mcmc_samples": 0, "interval_width": 0.8, "uncertainty_samples": 1000, "y_scale": 560000.0, "logistic_floor": false, "country_holidays": null, "component_modes": {"additive": ["yearly", "additive_terms", "extra_regressors_additive", "holidays"], "multiplicative": ["multiplicative_terms", "extra_regressors_multiplicative"]}, "changepoints": "{\"name\":\"ds\",\"index\":[1,2,3],\"data\":[\"2018-01-16T00:00:00.000\",\"2019-04-05T00:00:00.000\",\"2021-11-08T00:00:00.000\"]}", "history_dates": "{\"name\":\"ds\",\"index\":[0,1,2,3,4],\"data\":[\"2017-04-03T00:00:00.000\",\"2018-01-16T00:00:00.000\",\"2019-04-05T00:00:00.000\",\"2021-11-08T00:00:00.000\",\"2022-09-16T00:00:00.000\"]}", "train_holiday_names": null, "start": 1491177600.0, "t_scale": 172108800.0, "holidays": null, "history": "{\"schema\":{\"fields\":[{\"name\":\"y\",\"type\":\"number\"},{\"name\":\"ds\",\"type\":\"datetime\"},{\"name\":\"floor\",\"type\":\"integer\"},{\"name\":\"t\",\"type\":\"number\"},{\"name\":\"y_scaled\",\"type\":\"number\"}],\"pandas_version\":\"1.4.0\"},\"data\":[{\"y\":360000.0,\"ds\":\"2017-04-03T00:00:00.000\",\"floor\":0,\"t\":0.0,\"y_scaled\":0.6428571429},{\"y\":255000.0,\"ds\":\"2018-01-16T00:00:00.000\",\"floor\":0,\"t\":0.1445783133,\"y_scaled\":0.4553571429},{\"y\":485000.0,\"ds\":\"2019-04-05T00:00:00.000\",\"floor\":0,\"t\":0.3674698795,\"y_scaled\":0.8660714286},{\"y\":560000.0,\"ds\":\"2021-11-08T00:00:00.000\",\"floor\":0,\"t\":0.843373494,\"y_scaled\":1.0},{\"y\":500000.0,\"ds\":\"2022-09-16T00:00:00.000\",\"floor\":0,\"t\":1.0,\"y_scaled\":0.8928571429}]}", "train_component_cols": "{\"schema\":{\"fields\":[{\"name\":\"additive_terms\",\"type\":\"integer\"},{\"name\":\"yearly\",\"type\":\"integer\"},{\"name\":\"multiplicative_terms\",\"type\":\"integer\"}],\"pandas_version\":\"1.4.0\"},\"data\":[{\"additive_terms\":1,\"yearly\":1,\"multiplicative_terms\":0},{\"additive_terms\":1,\"yearly\":1,\"multiplicative_terms\":0},{\"additive_terms\":1,\"yearly\":1,\"multiplicative_terms\":0},{\"additive_terms\":1,\"yearly\":1,\"multiplicative_terms\":0},{\"additive_terms\":1,\"yearly\":1,\"multiplicative_terms\":0},{\"additive_terms\":1,\"yearly\":1,\"multiplicative_terms\":0},{\"additive_terms\":1,\"yearly\":1,\"multiplicative_terms\":0},{\"additive_terms\":1,\"yearly\":1,\"multiplicative_terms\":0},{\"additive_terms\":1,\"yearly\":1,\"multiplicative_terms\":0},{\"additive_terms\":1,\"yearly\":1,\"multiplicative_terms\":0},{\"additive_terms\":1,\"yearly\":1,\"multiplicative_terms\":0},{\"additive_terms\":1,\"yearly\":1,\"multiplicative_terms\":0},{\"additive_terms\":1,\"yearly\":1,\"multiplicative_terms\":0},{\"additive_terms\":1,\"yearly\":1,\"multiplicative_terms\":0},{\"additive_terms\":1,\"yearly\":1,\"multiplicative_terms\":0},{\"additive_terms\":1,\"yearly\":1,\"multiplicative_terms\":0},{\"additive_terms\":1,\"yearly\":1,\"multiplicative_terms\":0},{\"additive_terms\":1,\"yearly\":1,\"multiplicative_terms\":0},{\"additive_terms\":1,\"yearly\":1,\"multiplicative_terms\":0},{\"additive_terms\":1,\"yearly\":1,\"multiplicative_terms\":0}]}", "changepoints_t": [0.14457831325301204, 0.3674698795180723, 0.8433734939759037], "seasonalities": [["yearly"], {"yearly": {"period": 365.25, "fourier_order": 10, "prior_scale": 10.0, "mode": "additive", "condition_name": null}}], "extra_regressors": [[], {}], "fit_kwargs": {}, "params": {"lp__": [[108.283]], "k": [[-1.7144]], "m": [[-2.03083]], "delta": [[-1.13847e-09, -4.54123e-10, 2.47304e-10]], "sigma_obs": [[3.52978e-10]], "beta": [[-1.52722, 4.52905, -1.59889, -2.61019, -0.260932, 1.38216, 2.66531, 1.48631, -1.5755, -1.34034, 0.030697, -2.59139, 1.65031, -0.894988, -2.51149, 1.2751, -0.345753, -3.4813, -0.800738, 0.986577]], "trend": [[-2.03083, -2.2787, -2.66082, -3.47671, -3.74523]]}, "__prophet_version": "1.1.2"}