{"growth": "linear", "n_changepoints": 0, "specified_changepoints": false, "changepoint_range": 0.8, "yearly_seasonality": "auto", "weekly_seasonality": "auto", "daily_seasonality": "auto", "seasonality_mode": "additive", "seasonality_prior_scale": 10.0, "changepoint_prior_scale": 0.05, "holidays_prior_scale": 10.0, "mcmc_samples": 0, "interval_width": 0.8, "uncertainty_samples": 1000, "y_scale": 260000.0, "logistic_floor": false, "country_holidays": null, "component_modes": {"additive": ["yearly", "additive_terms", "extra_regressors_additive", "holidays"], "multiplicative": ["multiplicative_terms", "extra_regressors_multiplicative"]}, "changepoints": "{\"name\":\"ds\",\"index\":[],\"data\":[]}", "history_dates": "{\"name\":\"ds\",\"index\":[0,1],\"data\":[\"2018-01-10T00:00:00.000\",\"2022-07-11T00:00:00.000\"]}", "train_holiday_names": null, "start": 1515542400.0, "t_scale": 141955200.0, "holidays": null, "history": "{\"schema\":{\"fields\":[{\"name\":\"y\",\"type\":\"number\"},{\"name\":\"ds\",\"type\":\"datetime\"},{\"name\":\"floor\",\"type\":\"integer\"},{\"name\":\"t\",\"type\":\"number\"},{\"name\":\"y_scaled\",\"type\":\"number\"}],\"pandas_version\":\"1.4.0\"},\"data\":[{\"y\":233300.0,\"ds\":\"2018-01-10T00:00:00.000\",\"floor\":0,\"t\":0.0,\"y_scaled\":0.8973076923},{\"y\":260000.0,\"ds\":\"2022-07-11T00:00:00.000\",\"floor\":0,\"t\":1.0,\"y_scaled\":1.0}]}", "train_component_cols": "{\"schema\":{\"fields\":[{\"name\":\"additive_terms\",\"type\":\"integer\"},{\"name\":\"yearly\",\"type\":\"integer\"},{\"name\":\"multiplicative_terms\",\"type\":\"integer\"}],\"pandas_version\":\"1.4.0\"},\"data\":[{\"additive_terms\":1,\"yearly\":1,\"multiplicative_terms\":0},{\"additive_terms\":1,\"yearly\":1,\"multiplicative_terms\":0},{\"additive_terms\":1,\"yearly\":1,\"multiplicative_terms\":0},{\"additive_terms\":1,\"yearly\":1,\"multiplicative_terms\":0},{\"additive_terms\":1,\"yearly\":1,\"multiplicative_terms\":0},{\"additive_terms\":1,\"yearly\":1,\"multiplicative_terms\":0},{\"additive_terms\":1,\"yearly\":1,\"multiplicative_terms\":0},{\"additive_terms\":1,\"yearly\":1,\"multiplicative_terms\":0},{\"additive_terms\":1,\"yearly\":1,\"multiplicative_terms\":0},{\"additive_terms\":1,\"yearly\":1,\"multiplicative_terms\":0},{\"additive_terms\":1,\"yearly\":1,\"multiplicative_terms\":0},{\"additive_terms\":1,\"yearly\":1,\"multiplicative_terms\":0},{\"additive_terms\":1,\"yearly\":1,\"multiplicative_terms\":0},{\"additive_terms\":1,\"yearly\":1,\"multiplicative_terms\":0},{\"additive_terms\":1,\"yearly\":1,\"multiplicative_terms\":0},{\"additive_terms\":1,\"yearly\":1,\"multiplicative_terms\":0},{\"additive_terms\":1,\"yearly\":1,\"multiplicative_terms\":0},{\"additive_terms\":1,\"yearly\":1,\"multiplicative_terms\":0},{\"additive_terms\":1,\"yearly\":1,\"multiplicative_terms\":0},{\"additive_terms\":1,\"yearly\":1,\"multiplicative_terms\":0}]}", "changepoints_t": [0], "seasonalities": [["yearly"], {"yearly": {"period": 365.25, "fourier_order": 10, "prior_scale": 10.0, "mode": "additive", "condition_name": null}}], "extra_regressors": [[], {}], "fit_kwargs": {}, "params": {"lp__": [[47.8228]], "k": [[1.43450000431693]], "m": [[0.573941]], "delta": [[0.0]], "sigma_obs": [[1.10417e-11]], "beta": [[-3.65721, 1.02881, -0.597931, 1.68831, -0.485422, 2.06591, 0.0304435, -1.91261, -2.74059, 1.28205, 0.0403501, 4.44258, -0.495228, -8.50444, 2.43375, 0.742835, 1.23948, 9.68201, -4.01983, -16.5063]], "trend": [[0.573941, 2.00844]]}, "__prophet_version": "1.1.2"}